gimera.py
gimera-0.3.21.dist-info/LICENSE.txt
gimera-0.3.21.dist-info/METADATA
gimera-0.3.21.dist-info/WHEEL
gimera-0.3.21.dist-info/entry_points.txt
gimera-0.3.21.dist-info/top_level.txt
gimera-0.3.21.dist-info/RECORD
