Metadata-Version: 2.1
Name: gimera
Version: 0.3.21
Summary: Handling git submodules and patches.
Home-page: https://github.com/marcwimmer/gimera
Author: Marc-Christian Wimmer
Author-email: marc@itewimmer.de
License: MIT
Platform: UNKNOWN
Classifier: License :: OSI Approved :: MIT License
Classifier: Programming Language :: Python
Classifier: Programming Language :: Python :: 3
Classifier: Programming Language :: Python :: 3.6
Classifier: Programming Language :: Python :: Implementation :: CPython
Classifier: Programming Language :: Python :: Implementation :: PyPy
Requires-Python: >=3.6.0
License-File: LICENSE.txt
Requires-Dist: gitpython
Requires-Dist: click
Requires-Dist: inquirer
Requires-Dist: pyyaml
Requires-Dist: pathlib
